sanitipy/__init__.py
sanitipy/preprocessor.py
sanitipy/sanitipy.py
sanitipy/validator.py
sanitipy/visualizations.py
sanitipy-1.1.0.dist-info/licenses/LICENSE
sanitipy-1.1.0.dist-info/METADATA
sanitipy-1.1.0.dist-info/WHEEL
sanitipy-1.1.0.dist-info/top_level.txt
sanitipy-1.1.0.dist-info/RECORD
