Metadata-Version: 2.4
Name: sanitipy
Version: 1.1.0
Summary: Sanitipy is a user-friendly Python library designed for data cleaning and preprocessing. It provides essential utilities to streamline the process of preparing datasets for analysis or modeling. With features such as duplicate removal, handling missing values, and automatic data type inference, sanitipy simplifies the data cleaning workflow, making it a useful tool for data scientists and analysts.
Home-page: https://github.com/yestab335/sanitipy
Download-URL: 
Author: Adam Ben-Aamr
Author-email: adambenaamr@gmail.com
License: MIT
Keywords: data,data cleaning,missing data,data science,pandas,python
Classifier: Development Status :: 5 - Production/Stable
Classifier: Intended Audience :: Developers
License-File: LICENSE
Requires-Dist: pandas
Requires-Dist: missingno
Dynamic: author
Dynamic: author-email
Dynamic: classifier
Dynamic: description
Dynamic: description-content-type
Dynamic: home-page
Dynamic: keywords
Dynamic: license
Dynamic: license-file
Dynamic: requires-dist
Dynamic: summary
